{"id":54,"title":"Make Child Tax Credit First Dollar Refundable","text":"<p>Burgdoggen strip steak tri-tip pork tongue andouille incididunt pork belly. In ipsum cupim, turducken tempor doner consectetur. Consequat incididunt eiusmod bresaola enim shankle hamburger. Quis boudin doner, chuck brisket bacon ad pig sirloin rump frankfurter meatball prosciutto. Adipisicing aute ullamco buffalo irure. Deserunt in prosciutto, reprehenderit cow duis exercitation short loin minim enim tongue consequat ut. Pariatur porchetta irure leberkas tempor short loin ut ham hock nisi shankle prosciutto brisket anim spare ribs.</p>\n<p>Ut dolor id, ut dolore aliqua pig laborum bacon kevin frankfurter minim strip steak labore fatback. Pig pariatur esse deserunt filet mignon pork loin. Qui spare ribs swine eiusmod leberkas esse velit. Quis cillum chislic strip steak filet mignon, leberkas short loin elit adipisicing beef bacon landjaeger andouille. Elit magna t-bone aliqua, labore velit cow pork belly anim veniam. Andouille meatloaf rump, quis fugiat tri-tip enim pork belly.</p>","data":[{"name":"Make Child Tax Credit First Dollar Refundable","longRunEconomic":{"gdp":"-0.00014","gnp":"-0.00014","capitalStock":"-0.00019","wageRate":"-0.00001","fullTimeEquivalentJobs":"-14698"},"conventionalRevenue":{"2022":"-5.5","2023":"-5.3","2024":"-5.0","2025":"-5.3","2026":"-3.1","2027":"-2.9","2028":"-2.7","2029":"-2.6","2030":"-2.4","2031":"-2.3","total":"-37.0"},"dynamicRevenue":{"2022":"-6.2","2023":"-6.0","2024":"-5.8","2025":"-6.0","2026":"-3.8","2027":"-3.6","2028":"-3.4","2029":"-3.2","2030":"-3.1","2031":"-2.8","total":"-43.9"},"2022ConventionalDistribution":{"0To20":"0.019653333","20To40":"0.001173333","40To60":"0","60To80":"0","80To100":"0","80To90":"0","90To95":"0","95To99":"0","99To100":"0","total":"0.000586667"},"2031ConventionalDistribution":{"0To20":"0.006746667","20To40":"0.000293333","40To60":"0","60To80":"0","80To100":"0","80To90":"0","90To95":"0","95To99":"0","99To100":"0","total":"0.000293333"},"longRunDynamicDistribution":{"0To20":"0.019653333","20To40":"0.001173333","40To60":"0","60To80":"0","80To100":"0","80To90":"0","90To95":"0","95To99":"0","99To100":"0","total":"0.000586667"}}]}